{
  "location": {
    "githubOwner": "purescript-aws-sdk",
    "githubRepo": "purescript-aws-route53"
  },
  "published": {
    "0.0.1": {
      "bytes": 49315,
      "hash": "sha256-b9eKcQltMwAlZdyhC3pu5H4EmKCSD4eb8E41228ZIHg=",
      "publishedTime": "2018-03-10T21:34:31.0Z",
      "ref": "v0.0.1"
    },
    "0.1.1": {
      "bytes": 49478,
      "hash": "sha256-ip+RASF+sS7MhwsH+GgL7BEZErya565jHzbFIZYBrJI=",
      "publishedTime": "2018-03-12T18:18:50.0Z",
      "ref": "v0.1.1"
    },
    "0.1.2": {
      "bytes": 49453,
      "hash": "sha256-WYEw8StfXfOijoU8Lf3Y8atA+WA3fLJhoUuJ6HY3Kdk=",
      "publishedTime": "2018-03-13T13:39:07.0Z",
      "ref": "v0.1.2"
    },
    "0.2.1": {
      "bytes": 49148,
      "hash": "sha256-OIFwxUgxRbM2jQDPeK/m9U+PA3u/nk6ED6OrL7ctrp4=",
      "publishedTime": "2018-03-28T16:47:31.0Z",
      "ref": "v0.2.1"
    },
    "0.3.1": {
      "bytes": 48923,
      "hash": "sha256-GB4DzIVXgb84sx4Cekdph/4Rofd2tPUgE+kZZk/xCng=",
      "publishedTime": "2018-04-26T13:31:00.0Z",
      "ref": "v0.3.1"
    }
  },
  "unpublished": {}
}
