{
  "location": {
    "githubOwner": "purescript-aws-sdk",
    "githubRepo": "purescript-aws-redshift"
  },
  "published": {
    "0.0.1": {
      "bytes": 46395,
      "hash": "sha256-5RIcla4mo8+7XSLq/WeugnNdrZ4tNS59uvG6qMnpoq8=",
      "publishedTime": "2018-03-10T21:29:17.0Z",
      "ref": "v0.0.1"
    },
    "0.1.1": {
      "bytes": 46510,
      "hash": "sha256-yYdp9KAQC7h7UY4KNyPhl8Dfj0R3351QUxNRGYarX0c=",
      "publishedTime": "2018-03-12T18:17:04.0Z",
      "ref": "v0.1.1"
    },
    "0.1.2": {
      "bytes": 46485,
      "hash": "sha256-nOSfDoyhx7tXX7NDt1Ua0XXNXksxexUCor/hbaEcUSo=",
      "publishedTime": "2018-03-13T13:38:44.0Z",
      "ref": "v0.1.2"
    },
    "0.2.1": {
      "bytes": 45893,
      "hash": "sha256-CVVgLQV//OWxr3zvVv5Y6fNAKQxu2VSIJgaVdW+csZg=",
      "publishedTime": "2018-03-28T16:47:13.0Z",
      "ref": "v0.2.1"
    },
    "0.3.1": {
      "bytes": 45215,
      "hash": "sha256-RiZ6j6e4aH/dqPTgXveTm8xeskLe/BnObeYxTiHKUJs=",
      "publishedTime": "2018-04-26T13:30:37.0Z",
      "ref": "v0.3.1"
    }
  },
  "unpublished": {}
}
