{
  "location": {
    "githubOwner": "purescript-aws-sdk",
    "githubRepo": "purescript-aws-support"
  },
  "published": {
    "0.0.1": {
      "bytes": 17056,
      "hash": "sha256-sVOwq6pFjNRXQG6rUDMlzfEa/ydC5eG/TKh/aV5lvNw=",
      "publishedTime": "2018-03-10T21:56:46.0Z",
      "ref": "v0.0.1"
    },
    "0.1.1": {
      "bytes": 17088,
      "hash": "sha256-wIGnlojVis/xqG4DmDPssUplT5R3TBMYsXi4gAAAG0w=",
      "publishedTime": "2018-03-12T18:27:30.0Z",
      "ref": "v0.1.1"
    },
    "0.1.2": {
      "bytes": 17060,
      "hash": "sha256-ue8UW0Eq53MfNPc+W006RVpBGZrv8l4OVRsdkjdoQhM=",
      "publishedTime": "2018-03-13T13:40:41.0Z",
      "ref": "v0.1.2"
    },
    "0.2.1": {
      "bytes": 17075,
      "hash": "sha256-uveNYKXyoj1CgDjcIj51whH9Mqq/DgpIIXYOi0OUWOs=",
      "publishedTime": "2018-03-28T16:49:16.0Z",
      "ref": "v0.2.1"
    },
    "0.3.1": {
      "bytes": 16938,
      "hash": "sha256-RDa5WPAiS0hpZtSH8l3wc9iJUnUrLO+hQtygkCCKEq8=",
      "publishedTime": "2018-04-26T13:33:11.0Z",
      "ref": "v0.3.1"
    }
  },
  "unpublished": {}
}
