{
  "location": {
    "githubOwner": "Unisay",
    "githubRepo": "purescript-binary"
  },
  "published": {
    "0.0.1": {
      "bytes": 4121,
      "compilers": [
        "0.13.0",
        "0.13.2",
        "0.13.3",
        "0.13.4",
        "0.13.5",
        "0.13.6",
        "0.13.8"
      ],
      "hash": "sha256-Rr9VjNPdkLm+2oYZfusrNXJfLlsxTsADOTkTjvrDxlM=",
      "publishedTime": "2017-10-17T20:27:08.000Z"
    },
    "0.0.2": {
      "bytes": 4161,
      "compilers": [
        "0.13.0",
        "0.13.2",
        "0.13.3",
        "0.13.4",
        "0.13.5",
        "0.13.6",
        "0.13.8"
      ],
      "hash": "sha256-WL09/N5NQzt0cAxiSZykBdh3gFkgNSqH+/Q9RqbRgwM=",
      "publishedTime": "2017-10-18T15:53:51.000Z"
    },
    "0.0.3": {
      "bytes": 4164,
      "compilers": [
        "0.13.0",
        "0.13.2",
        "0.13.3",
        "0.13.4",
        "0.13.5",
        "0.13.6",
        "0.13.8"
      ],
      "hash": "sha256-QB7b54EQrj/6IZ4AOxgUvMokrc9VWGK+8qMab7ePRzk=",
      "publishedTime": "2017-10-18T15:59:56.000Z"
    },
    "0.0.4": {
      "bytes": 5263,
      "compilers": [
        "0.13.0",
        "0.13.2",
        "0.13.3",
        "0.13.4",
        "0.13.5",
        "0.13.6",
        "0.13.8"
      ],
      "hash": "sha256-MwZOSn8ucmokpzu68TKWcdcua0DtcAMSkkbCZwW8l6o=",
      "publishedTime": "2017-10-22T17:34:00.000Z"
    },
    "0.0.5": {
      "bytes": 5262,
      "compilers": [
        "0.13.0",
        "0.13.2",
        "0.13.3",
        "0.13.4",
        "0.13.5",
        "0.13.6",
        "0.13.8"
      ],
      "hash": "sha256-gH5RgSJm83x2BS4DRlNY1Oe2PbtnlkBUvRGUAKvrAQ0=",
      "publishedTime": "2017-10-22T17:34:27.000Z"
    },
    "0.0.6": {
      "bytes": 5358,
      "compilers": [
        "0.13.0",
        "0.13.2",
        "0.13.3",
        "0.13.4",
        "0.13.5",
        "0.13.6",
        "0.13.8"
      ],
      "hash": "sha256-sI2OzsHrnB5drX9VWs6HpzpSr+GkeSwYCeotb4BfN/w=",
      "publishedTime": "2017-10-22T17:48:26.000Z"
    },
    "0.0.7": {
      "bytes": 5425,
      "compilers": [
        "0.13.0",
        "0.13.2",
        "0.13.3",
        "0.13.4",
        "0.13.5",
        "0.13.6",
        "0.13.8"
      ],
      "hash": "sha256-Ool6TbBBN+vzAT7U+zpP5bE8rg7Erf+5SaO0OEtRnFY=",
      "publishedTime": "2017-10-22T20:54:30.000Z"
    },
    "0.0.8": {
      "bytes": 5221,
      "compilers": [
        "0.13.0",
        "0.13.2",
        "0.13.3",
        "0.13.4",
        "0.13.5",
        "0.13.6",
        "0.13.8"
      ],
      "hash": "sha256-OyE5M5PUn7IAm8bmGKVIMb9RV/nD0C7G26/zIvqp6Io=",
      "publishedTime": "2017-10-22T21:29:21.000Z"
    },
    "0.0.9": {
      "bytes": 5502,
      "compilers": [
        "0.13.0",
        "0.13.2",
        "0.13.3",
        "0.13.4",
        "0.13.5",
        "0.13.6",
        "0.13.8"
      ],
      "hash": "sha256-eBPqq2ngk6vyCA1MkwgjFV+NLW/WgB0s4UaepI3PKjc=",
      "publishedTime": "2017-10-23T15:00:36.000Z"
    },
    "0.0.10": {
      "bytes": 5537,
      "compilers": [
        "0.13.0",
        "0.13.2",
        "0.13.3",
        "0.13.4",
        "0.13.5",
        "0.13.6",
        "0.13.8"
      ],
      "hash": "sha256-9D+1MRcUL80YBBlsZZ7wslP2gIsJVi7VAjrydk/1Dg0=",
      "publishedTime": "2017-10-23T16:16:54.000Z"
    },
    "0.0.11": {
      "bytes": 5910,
      "compilers": [
        "0.13.0",
        "0.13.2",
        "0.13.3",
        "0.13.4",
        "0.13.5",
        "0.13.6",
        "0.13.8"
      ],
      "hash": "sha256-b8gj5+aAzh2suvwusujhaA6/0QBCgFJ2kANH9rQW18Q=",
      "publishedTime": "2017-10-24T17:34:32.000Z"
    },
    "0.0.12": {
      "bytes": 5931,
      "compilers": [
        "0.13.0",
        "0.13.2",
        "0.13.3",
        "0.13.4",
        "0.13.5",
        "0.13.6",
        "0.13.8"
      ],
      "hash": "sha256-8gWabbEa8ElqbhTMNwHnVJDydfV2Hlf32Q/mYKhUKGY=",
      "publishedTime": "2017-10-24T20:35:34.000Z"
    },
    "0.0.13": {
      "bytes": 6063,
      "compilers": [
        "0.13.0",
        "0.13.2",
        "0.13.3",
        "0.13.4",
        "0.13.5",
        "0.13.6",
        "0.13.8"
      ],
      "hash": "sha256-Cdm0y8i7+8pLEG5ZA+cqENId8/2cZNBcQyZPs4GUODU=",
      "publishedTime": "2017-10-25T20:08:46.000Z"
    },
    "0.0.14": {
      "bytes": 6137,
      "compilers": [
        "0.13.0",
        "0.13.2",
        "0.13.3",
        "0.13.4",
        "0.13.5",
        "0.13.6",
        "0.13.8"
      ],
      "hash": "sha256-CaeDQLOgE8hr+VUZlePS+cUegUfd3ryosdokYFBhvV4=",
      "publishedTime": "2017-10-26T11:34:45.000Z"
    },
    "0.0.15": {
      "bytes": 6433,
      "compilers": [
        "0.13.0",
        "0.13.2",
        "0.13.3",
        "0.13.4",
        "0.13.5",
        "0.13.6",
        "0.13.8"
      ],
      "hash": "sha256-1IsRfj1jnSwZ25bdww+NGDbL7HZmPrI/VO7Ju3DMihE=",
      "publishedTime": "2017-10-26T19:27:33.000Z"
    },
    "0.0.16": {
      "bytes": 6498,
      "compilers": [
        "0.13.0",
        "0.13.2",
        "0.13.3",
        "0.13.4",
        "0.13.5",
        "0.13.6",
        "0.13.8"
      ],
      "hash": "sha256-qorUobGq12GUHuF52+SbNWaGrEbSrW5MYxvG6oVc2x4=",
      "publishedTime": "2017-10-27T17:18:25.000Z"
    },
    "0.0.17": {
      "bytes": 6531,
      "compilers": [
        "0.13.0",
        "0.13.2",
        "0.13.3",
        "0.13.4",
        "0.13.5",
        "0.13.6",
        "0.13.8"
      ],
      "hash": "sha256-/czPPPc2HTGT8xuXwZ1C6SEPhA0ZklRbrA0Ir+fUPLk=",
      "publishedTime": "2017-10-29T23:11:37.000Z"
    },
    "0.0.18": {
      "bytes": 6573,
      "compilers": [
        "0.13.0",
        "0.13.2",
        "0.13.3",
        "0.13.4",
        "0.13.5",
        "0.13.6",
        "0.13.8"
      ],
      "hash": "sha256-CkmM7naB8Pg0/94vuVcpcC7DX67u/RP+YStrWhCUB70=",
      "publishedTime": "2017-10-30T10:43:27.000Z"
    },
    "0.0.19": {
      "bytes": 6627,
      "compilers": [
        "0.13.0",
        "0.13.2",
        "0.13.3",
        "0.13.4",
        "0.13.5",
        "0.13.6",
        "0.13.8"
      ],
      "hash": "sha256-RRF5fXhavBr7l96eFJOxQlhTqOb3hu1m54AileMZqdg=",
      "publishedTime": "2017-10-30T13:29:18.000Z"
    },
    "0.0.20": {
      "bytes": 6641,
      "compilers": [
        "0.13.0",
        "0.13.2",
        "0.13.3",
        "0.13.4",
        "0.13.5",
        "0.13.6",
        "0.13.8"
      ],
      "hash": "sha256-/ZGtIjdaxp8MNubKSZZ9JAJj429P2GQxPUyHTH0+7Fo=",
      "publishedTime": "2017-10-30T15:15:38.000Z"
    },
    "0.0.21": {
      "bytes": 6678,
      "compilers": [
        "0.13.0",
        "0.13.2",
        "0.13.3",
        "0.13.4",
        "0.13.5",
        "0.13.6",
        "0.13.8"
      ],
      "hash": "sha256-kmBjrtEIU7naEQmTLFAuMtqh6wvtZleU/RF0vKw8478=",
      "publishedTime": "2017-10-30T15:54:01.000Z"
    },
    "0.1.0": {
      "bytes": 7104,
      "compilers": [
        "0.13.0",
        "0.13.2",
        "0.13.3",
        "0.13.4",
        "0.13.5",
        "0.13.6",
        "0.13.8"
      ],
      "hash": "sha256-LeF/32DovBM7XVECKRoaNW31Ng9sMlMhdnSXL/G9UBs=",
      "publishedTime": "2017-10-31T16:32:47.000Z"
    },
    "0.1.1": {
      "bytes": 7185,
      "compilers": [
        "0.13.0",
        "0.13.2",
        "0.13.3",
        "0.13.4",
        "0.13.5",
        "0.13.6",
        "0.13.8"
      ],
      "hash": "sha256-Rj2Vs+uxoUmPKSGqxxEegkk5M+TxsM3zMnwmWhIa4VE=",
      "publishedTime": "2017-10-31T21:43:15.000Z"
    }
  },
  "unpublished": {}
}
