{
  "location": {
    "githubOwner": "Bucketchain",
    "githubRepo": "purescript-bucketchain-static"
  },
  "published": {
    "0.1.0": {
      "bytes": 5412,
      "hash": "sha256-NQyEM5wMHEdNwB4feJmFa8hi6bwZCsMmuqsNIzAItGA=",
      "publishedTime": "2018-11-27T15:31:46.0Z",
      "ref": "v0.1.0"
    },
    "0.2.0": {
      "bytes": 5402,
      "hash": "sha256-pHwQcbHoXRgYEdhApbFzmi8l074KQnyzcMkYxZh1mGk=",
      "publishedTime": "2018-12-20T02:41:58.0Z",
      "ref": "v0.2.0"
    },
    "0.3.0": {
      "bytes": 5474,
      "hash": "sha256-+XzNVSfNiGyYFqdbuxVZOjB7N93xkq6ZxDvTdwfiKj0=",
      "publishedTime": "2019-06-09T14:22:29.0Z",
      "ref": "v0.3.0"
    },
    "0.4.0": {
      "bytes": 5478,
      "hash": "sha256-TeBdBU3UYo8Tl6NdfxUjY1pvsAzQcPl4m/0ajh97EDk=",
      "publishedTime": "2021-03-02T07:18:06.0Z",
      "ref": "v0.4.0"
    }
  },
  "unpublished": {}
}
