{
  "location": {
    "githubOwner": "slamdata",
    "githubRepo": "purescript-chalky"
  },
  "published": {
    "0.1.0": {
      "bytes": 5145,
      "hash": "sha256-j0YY+PChdnkoxNNF9NjGPBklT4MkzMCXs0H07ZjvH3A=",
      "publishedTime": "2015-10-26T03:23:00.0Z",
      "ref": "v0.1.0"
    },
    "0.2.0": {
      "bytes": 5134,
      "hash": "sha256-xKvCZ6HNMcEughZkv6CdHXrtElHqlqJAGKpWD6zY24Q=",
      "publishedTime": "2015-10-26T03:38:14.0Z",
      "ref": "v0.2.0"
    },
    "1.0.0": {
      "bytes": 5144,
      "hash": "sha256-pSKaoyYCuQ0938F7rYYgnb1nL3OpOkbBu1668eHHHo4=",
      "publishedTime": "2016-07-24T20:36:44.0Z",
      "ref": "v1.0.0"
    },
    "2.0.0": {
      "bytes": 5145,
      "hash": "sha256-wk+0WjNc111gel7oIdTDfLZ1GVb/eWtjZr2X2Co6KN0=",
      "publishedTime": "2016-11-03T16:01:44.0Z",
      "ref": "v2.0.0"
    }
  },
  "unpublished": {}
}
