{
  "location": {
    "githubOwner": "collegevine",
    "githubRepo": "purescript-elmish-hooks"
  },
  "published": {
    "0.0.1": {
      "bytes": 5559,
      "hash": "sha256-7VmLuJgJARhKX18s/q7DW9R5lTb0JRoO1BNj5vfdDxM=",
      "publishedTime": "2021-12-21T21:49:54.000Z",
      "ref": "v0.0.1"
    },
    "0.1.0": {
      "bytes": 6160,
      "hash": "sha256-J1bc1VVenbmEG3ZaYjRyIs8zX+QqLaCBLQOVxXzqAeM=",
      "publishedTime": "2021-12-24T04:48:12.000Z",
      "ref": "v0.1.0"
    },
    "0.2.0": {
      "bytes": 6368,
      "hash": "sha256-kreau600H+7bWOk9qt/voAKmsv5cCXvKH10RT6OAF4s=",
      "publishedTime": "2021-12-26T18:52:41.000Z",
      "ref": "v0.2.0"
    },
    "0.3.0": {
      "bytes": 6593,
      "hash": "sha256-mFE5XBZVazpzjK0I9zBUqTX8zQzKFME6xRe9nrUQCqQ=",
      "publishedTime": "2021-12-27T22:01:37.000Z",
      "ref": "v0.3.0"
    },
    "0.3.1": {
      "bytes": 6592,
      "hash": "sha256-Rx8zlG2U0iU6epNyU1U/vS3Oj1cwcemrFMcZht6L6vI=",
      "publishedTime": "2021-12-27T22:09:36.000Z",
      "ref": "v0.3.1"
    },
    "0.4.0": {
      "bytes": 7312,
      "hash": "sha256-h8x6hNRBliHZRgJ8z62gkGn/8mfOgML3+gwN+5svIqY=",
      "publishedTime": "2022-01-03T14:58:00.000Z",
      "ref": "v0.4.0"
    },
    "0.4.1": {
      "bytes": 7118,
      "hash": "sha256-Z0Gx64zz8eIz821DwewAY5GjdTBpTHMvlypHRVtC2fg=",
      "publishedTime": "2022-01-13T00:39:27.000Z",
      "ref": "v0.4.1"
    },
    "0.4.2": {
      "bytes": 7148,
      "hash": "sha256-e5heWi9CvO+Zs9YdKY/eVWqS24MqXF2JtKcG3XSKP44=",
      "publishedTime": "2022-01-14T02:11:01.000Z",
      "ref": "v0.4.2"
    },
    "0.5.0": {
      "bytes": 7234,
      "hash": "sha256-nL9EQIzyheM3f4lNntqZzEbuGppdZTTCz7QyAxfP3Wk=",
      "publishedTime": "2022-01-18T21:10:47.000Z",
      "ref": "v0.5.0"
    },
    "0.5.1": {
      "bytes": 7532,
      "hash": "sha256-zUw3tmYICM/YpN1pPTG12N0rqAgY1cY2iw3OwOwL8JU=",
      "publishedTime": "2022-01-19T15:09:23.000Z",
      "ref": "v0.5.1"
    },
    "0.5.2": {
      "bytes": 7501,
      "hash": "sha256-oOhzgdeCLWS3qxrDRHjyFif5I0IFoKFdVu3NkpUe/PE=",
      "publishedTime": "2022-01-20T18:22:28.000Z",
      "ref": "v0.5.2"
    },
    "0.6.0": {
      "bytes": 7874,
      "hash": "sha256-eioJhwkHuMjoItgscflAfD1xQNE5aDBm0fDhzalC4+8=",
      "publishedTime": "2022-04-20T16:22:28.000Z",
      "ref": "v0.6.0"
    },
    "0.6.1": {
      "bytes": 7893,
      "hash": "sha256-pdoGXDqRJTE6AZkMzPrehvLdSvqwXYqXdjfnDwIjLKU=",
      "publishedTime": "2022-04-20T16:40:10.000Z",
      "ref": "v0.6.1"
    },
    "0.7.0": {
      "bytes": 7928,
      "hash": "sha256-2XdYYDJFHNNs2C095CxH6RZLyRSKqfPfxTnBkFlYeZE=",
      "publishedTime": "2022-04-28T13:57:57.000Z",
      "ref": "v0.7.0"
    },
    "0.8.0": {
      "bytes": 8239,
      "hash": "sha256-aOA0+pG5M32N/6WY0q2TCHb3Nc8U4bNTfVCp2OEk6Ug=",
      "publishedTime": "2022-04-30T04:21:01.000Z",
      "ref": "v0.8.0"
    },
    "0.8.1": {
      "bytes": 8172,
      "hash": "sha256-tdPqNNk3peS3MUSanJvk5j+PDiJNq6HcH/Xhpmow9Fk=",
      "publishedTime": "2022-06-14T18:37:16.000Z",
      "ref": "v0.8.1"
    },
    "0.8.2": {
      "bytes": 8173,
      "hash": "sha256-2MclsRzgbBoeHKVlfz0eYXGmch6IGlyobVww6XbflWo=",
      "publishedTime": "2022-06-14T18:44:24.000Z",
      "ref": "v0.8.2"
    },
    "0.8.3": {
      "bytes": 7883,
      "hash": "sha256-+wHR3tMzKnNe0V565IOWLxsJ5GJ7Py/TYlK49Yaev94=",
      "publishedTime": "2022-10-18T14:22:22.000Z",
      "ref": "v0.8.3"
    },
    "0.9.0": {
      "bytes": 7918,
      "hash": "sha256-ZzwaojRwgTri9bSQtteqp8FJVRqt7lWeZ80OmaPaIU4=",
      "publishedTime": "2022-12-21T16:38:56.000Z",
      "ref": "v0.9.0"
    },
    "0.9.1": {
      "bytes": 7908,
      "hash": "sha256-lm9Sdp+knZgVYc784dSS4l7ICE0SmOLGYHSvtlgWwbg=",
      "publishedTime": "2023-01-02T16:17:09.000Z",
      "ref": "v0.9.1"
    },
    "0.10.0": {
      "bytes": 7880,
      "hash": "sha256-a2FZtH+5Z8puIDFtTq1BhISQjDpCTa9LiQuXR380yp0=",
      "publishedTime": "2023-09-30T07:18:12.862Z",
      "ref": "v0.10.0"
    }
  },
  "unpublished": {}
}
