{
  "location": {
    "githubOwner": "rowtype-yoga",
    "githubRepo": "purescript-fetch-argonaut"
  },
  "published": {
    "1.0.0": {
      "bytes": 2995,
      "hash": "sha256-86D6rYPiHz/GD8pdEpRASV3d+COULjz/qCQF9+1UzOo=",
      "publishedTime": "2022-08-20T19:53:52.000Z",
      "ref": "v1.0.0"
    },
    "1.0.1": {
      "bytes": 2985,
      "hash": "sha256-tQwOBM5JbuXwPVOBDeREEdvXhY0eioFDqLWBMl1LkYo=",
      "publishedTime": "2023-04-07T07:27:37.000Z",
      "ref": "v1.0.1"
    }
  },
  "unpublished": {}
}
