{
  "location": {
    "githubOwner": "aij",
    "githubRepo": "purescript-halogen-pure"
  },
  "published": {
    "0.0.1": {
      "bytes": 2551,
      "hash": "sha256-+mxp57jvej1Y68nbuLkChH6IseSxodZkQ1XWpJCVUkA=",
      "publishedTime": "2019-07-08T18:37:25.0Z",
      "ref": "v0.0.1"
    },
    "0.0.2": {
      "bytes": 1386,
      "hash": "sha256-31zUU+O/yM/zQRHyQx1ZlpCFB/zIxCwVumYLaBXj+Jo=",
      "publishedTime": "2019-07-08T21:16:18.0Z",
      "ref": "v0.0.2"
    }
  },
  "unpublished": {}
}
