{
  "location": {
    "githubOwner": "narinari",
    "githubRepo": "purescript-js-barcode"
  },
  "published": {
    "0.1.0": {
      "bytes": 2101,
      "hash": "sha256-WQtHiTXAGRn6sRB6pdqfYu6cnQAyQeLo66lDlRIG53s=",
      "publishedTime": "2016-10-25T01:58:24.0Z",
      "ref": "0.1.0"
    },
    "1.0.0": {
      "bytes": 2094,
      "hash": "sha256-Sli/3sjnhj3N/UmpHiBNgutK7FmXtUgdgWustQp/NA4=",
      "publishedTime": "2016-11-09T06:24:34.0Z",
      "ref": "1.0.0"
    },
    "1.0.1": {
      "bytes": 2109,
      "hash": "sha256-bgC1YaRrvH3RYwRg6cJ9ONy7LYTLt/jhpITeoYVXpDo=",
      "publishedTime": "2017-03-20T15:05:53.0Z",
      "ref": "1.0.1"
    },
    "1.0.2": {
      "bytes": 2089,
      "hash": "sha256-4kSxbBKOnsRzIixPSk/yGja9VxnWLQwaCDkpAbK1gx0=",
      "publishedTime": "2017-03-30T22:40:55.0Z",
      "ref": "1.0.2"
    }
  },
  "unpublished": {}
}
