{
  "location": {
    "githubOwner": "felixschl",
    "githubRepo": "purescript-pipes-aff"
  },
  "published": {
    "0.0.1": {
      "bytes": 2022,
      "hash": "sha256-plpgI3xwWcc1zqKyOydA3xsBB6PIabWEc52b1Uem95Q=",
      "publishedTime": "2017-08-23T16:49:32.0Z",
      "ref": "v0.0.1"
    },
    "0.0.2": {
      "bytes": 2019,
      "hash": "sha256-dXFFFaxF7NmIqRU71vGBCzeoy/WM9zGw9XESMrLngYA=",
      "publishedTime": "2017-08-23T16:53:54.0Z",
      "ref": "v0.0.2"
    },
    "0.1.0": {
      "bytes": 2144,
      "hash": "sha256-33ib4p4MI9QKEjxujPfOmsDetcqdb9OPJXzfVgeLe5A=",
      "publishedTime": "2017-09-26T04:14:51.0Z",
      "ref": "v0.1.0"
    },
    "0.2.0": {
      "bytes": 2187,
      "hash": "sha256-y1UEZgbsDl0hMzRviaoIWJzkPaGUq44vHvOjBxtN8xQ=",
      "publishedTime": "2017-09-29T17:51:18.0Z",
      "ref": "v0.2.0"
    },
    "0.3.0": {
      "bytes": 2153,
      "hash": "sha256-SJ1J7qiHy6t2oCtAeUqf/n9lusFYG803GVg0OBkk6IY=",
      "publishedTime": "2017-10-03T15:30:35.0Z",
      "ref": "v0.3.0"
    },
    "0.4.0": {
      "bytes": 2060,
      "hash": "sha256-tux+9ZD9ZRoh4NJAlFkWUvbtJZ5UffAclORaATlJsaY=",
      "publishedTime": "2017-12-13T20:42:32.0Z",
      "ref": "v0.4.0"
    },
    "0.5.0": {
      "bytes": 2112,
      "hash": "sha256-vXnj/MOBxD3dmpUHjRS+Rr5KpFSiZShTwVGXfdi9uxM=",
      "publishedTime": "2018-04-19T09:35:24.0Z",
      "ref": "v0.5.0"
    }
  },
  "unpublished": {}
}
