{
  "location": {
    "githubOwner": "thimoteus",
    "githubRepo": "purescript-promises"
  },
  "published": {
    "0.1.0": {
      "bytes": 3278,
      "hash": "sha256-bhCIzvmzsQ2Enr85eucryXkVVy4Aa+W3B+N/9J6NP14=",
      "publishedTime": "2017-08-25T06:22:59.0Z",
      "ref": "v0.1.0"
    },
    "0.2.0": {
      "bytes": 3903,
      "hash": "sha256-7evucxwKRkI+dpeza+n9dqQsDwPNNrIRHgQsD8NIEec=",
      "publishedTime": "2017-08-28T13:51:29.0Z",
      "ref": "v0.2.0"
    },
    "1.0.0": {
      "bytes": 4470,
      "hash": "sha256-cAZq0+r9NoidCANdoGL+my5+0bqUiy2w4b54mQxFTuY=",
      "publishedTime": "2017-08-29T12:41:44.0Z",
      "ref": "v1.0.0"
    },
    "1.0.1": {
      "bytes": 5163,
      "hash": "sha256-jvggnaHzMeAbfDucwXWsK0WMEUBBfKNudlo6pYL31O8=",
      "publishedTime": "2017-08-30T01:44:06.0Z",
      "ref": "v1.0.1"
    },
    "2.0.0": {
      "bytes": 5995,
      "hash": "sha256-lt3MeL3KISYAzyiHBnH+QSZtbFoTpppWVMX9Frk2PF0=",
      "publishedTime": "2017-09-01T14:50:14.0Z",
      "ref": "v2.0.0"
    },
    "3.0.0": {
      "bytes": 5708,
      "hash": "sha256-hvZ5fBKWpZyd6X5ylW/78aWMLXzXGjmEvDR7OaydcyM=",
      "publishedTime": "2018-05-26T03:30:06.0Z",
      "ref": "v3.0.0"
    },
    "3.1.0": {
      "bytes": 5724,
      "hash": "sha256-S5AAsCPHBKHR6k67O2Ctu5as94eW1LLD9cyGS6818uQ=",
      "publishedTime": "2019-03-06T01:51:55.0Z",
      "ref": "v3.1.0"
    },
    "3.1.1": {
      "bytes": 5724,
      "hash": "sha256-xToELnNrtRbWf6xDp9DIwOAYoi3YowTtevjMSxB25lk=",
      "publishedTime": "2019-05-08T18:08:01.0Z",
      "ref": "v3.1.1"
    }
  },
  "unpublished": {}
}
