{
  "location": {
    "githubOwner": "slamdata",
    "githubRepo": "purescript-quasar"
  },
  "published": {
    "1.0.0": {
      "bytes": 15210,
      "hash": "sha256-uHqI2o0SdK3xmMU0T8sKd6NuxTxR/2ruGkhHEiBc9ss=",
      "publishedTime": "2016-04-22T10:28:25.0Z",
      "ref": "v1.0.0"
    },
    "1.1.0": {
      "bytes": 15503,
      "hash": "sha256-b0AR99LJvj8Q/Iac/U1TNQ1ekuEGVRF0igoTHi0sX6s=",
      "publishedTime": "2016-04-28T14:39:21.0Z",
      "ref": "v1.1.0"
    },
    "1.2.0": {
      "bytes": 15508,
      "hash": "sha256-z3Qa3MEjVhiAPQd8bml2qCxR/D9o+N3wN7FEiCf4Cyw=",
      "publishedTime": "2016-05-31T19:50:31.0Z",
      "ref": "v1.2.0"
    },
    "2.0.0": {
      "bytes": 19447,
      "hash": "sha256-GnD1UGsqrF/Lb9XWsC3utEhKZmC5UbJg3Ec3V1lbXIY=",
      "publishedTime": "2016-07-29T14:55:47.0Z",
      "ref": "v2.0.0"
    },
    "3.0.0": {
      "bytes": 19454,
      "hash": "sha256-zwPwxmqXjRdn5dK3BuTDrFGsRfPGPEJQI0opZOx6XEI=",
      "publishedTime": "2016-07-31T20:13:02.0Z",
      "ref": "v3.0.0"
    },
    "4.0.0": {
      "bytes": 19569,
      "hash": "sha256-xdw2CCtr5nl3QCVGyNfN0sEKhzxTw4k505kcsJm0Qbk=",
      "publishedTime": "2016-08-18T15:45:44.0Z",
      "ref": "v4.0.0"
    },
    "5.0.0": {
      "bytes": 19808,
      "hash": "sha256-aEumJa3oUUpINu2tcMYVZuqt51g+/8d9V3U89ADLJbE=",
      "publishedTime": "2016-08-29T21:46:28.0Z",
      "ref": "v5.0.0"
    },
    "6.0.0": {
      "bytes": 19986,
      "hash": "sha256-+n7ob1JrNJq3klHebXq3GlhLU5d3mb6zYfOpESgLjH8=",
      "publishedTime": "2016-10-14T23:12:39.0Z",
      "ref": "v6.0.0"
    },
    "7.0.0": {
      "bytes": 21192,
      "hash": "sha256-Djz6vFlyDT4K/ImZqEqypB4G9VzEIuKK9ghLqLJD+IY=",
      "publishedTime": "2016-10-18T19:06:03.0Z",
      "ref": "v7.0.0"
    },
    "8.0.0": {
      "bytes": 21273,
      "hash": "sha256-HAWq11mVwZvzYx9DWBYQTwjdWzG3iODA9EXdHnEg/qs=",
      "publishedTime": "2016-10-25T20:15:24.0Z",
      "ref": "v8.0.0"
    },
    "9.0.0": {
      "bytes": 21266,
      "hash": "sha256-9Ksww9oDjE4/yDr9e7uzXwxPgiZ66MIoUN9k5mX5TNA=",
      "publishedTime": "2016-11-01T19:58:24.0Z",
      "ref": "v9.0.0"
    },
    "10.0.0": {
      "bytes": 21462,
      "hash": "sha256-paO3wJFYG+d8fswIs9Wsv7yNd3fZNH1Hj/hVIsBFbYU=",
      "publishedTime": "2016-11-03T18:51:00.0Z",
      "ref": "v10.0.0"
    },
    "11.0.0": {
      "bytes": 21384,
      "hash": "sha256-gy+iQkI0SY+scIh1v69RNw1wHRrXprmjuGH+x6LPAgw=",
      "publishedTime": "2016-11-08T22:02:45.0Z",
      "ref": "v11.0.0"
    },
    "12.0.0": {
      "bytes": 21406,
      "hash": "sha256-ZlbJqE+7HFjXk6vrb7Fld9RUwKEvaNEyOCtr8G45rh4=",
      "publishedTime": "2016-11-28T17:35:30.0Z",
      "ref": "v12.0.0"
    },
    "13.0.0": {
      "bytes": 21087,
      "hash": "sha256-Doik211p/yFnZRYeRejcbEh95HR/Ddvupc1q+dBNWQw=",
      "publishedTime": "2017-01-04T15:18:23.0Z",
      "ref": "v13.0.0"
    },
    "14.0.0": {
      "bytes": 21243,
      "hash": "sha256-RC9qzpXiEOSn3b44nmviJFxUo7pdsZCbPGXJrF13y7Q=",
      "publishedTime": "2017-01-19T15:49:36.0Z",
      "ref": "v14.0.0"
    },
    "14.0.1": {
      "bytes": 21261,
      "hash": "sha256-CVHL4gf9uiMHx/j6wQZkd8SHXNOUAjOfGjzepXEnGMY=",
      "publishedTime": "2017-01-19T16:11:20.0Z",
      "ref": "v14.0.1"
    },
    "15.0.0": {
      "bytes": 21287,
      "hash": "sha256-gRZN5QA2MB6RiaUjSK5aUaXPcH3VeIYBuPn/NgHzrSg=",
      "publishedTime": "2017-03-07T12:37:13.0Z",
      "ref": "v15.0.0"
    },
    "16.0.0": {
      "bytes": 21287,
      "hash": "sha256-96LENnI3BEfWYWQJ4MuIdwV+DMU3GfQhUIFBQs4ClYQ=",
      "publishedTime": "2017-03-10T18:28:19.0Z",
      "ref": "v16.0.0"
    },
    "17.0.0": {
      "bytes": 21291,
      "hash": "sha256-fmetJiFtedqXpVjd99ny2ln1HYL5ChI7szYleqlmHAE=",
      "publishedTime": "2017-03-14T13:00:09.0Z",
      "ref": "v17.0.0"
    },
    "18.0.0": {
      "bytes": 21569,
      "hash": "sha256-nofWgUY3weKU4T/8SbAjC6sFXKy3twAqxX1Rn5+ZsB8=",
      "publishedTime": "2017-03-23T17:30:15.0Z",
      "ref": "v18.0.0"
    },
    "19.0.0": {
      "bytes": 21571,
      "hash": "sha256-ypMWr0qTuKTalbQ8PWkJ9aicIzdbdmLHzSwKPR5WbM4=",
      "publishedTime": "2017-03-28T11:16:20.0Z",
      "ref": "v19.0.0"
    },
    "20.0.0": {
      "bytes": 21712,
      "hash": "sha256-PvjBBWnmc6JrpGcOF/DnodRHaBYJ7INc1xgIEwH5COk=",
      "publishedTime": "2017-04-03T16:06:21.0Z",
      "ref": "v20.0.0"
    },
    "21.0.0": {
      "bytes": 21706,
      "hash": "sha256-CWE44X6nhQ29K53VgqQSlycSVPbFTXHXhC+otpnxrP8=",
      "publishedTime": "2017-04-19T15:22:11.0Z",
      "ref": "v21.0.0"
    },
    "22.0.0": {
      "bytes": 21690,
      "hash": "sha256-d+9ay2Xht9m6LJ4skS0z9TNnwmVOFIjotUYNNCM/Sgs=",
      "publishedTime": "2017-04-21T19:44:21.0Z",
      "ref": "v22.0.0"
    },
    "23.0.0": {
      "bytes": 22024,
      "hash": "sha256-zyEUByl3Ae4eO4Wxcp4Xi+D19P+Z1/KDWxabuxl/t8I=",
      "publishedTime": "2017-04-28T16:50:28.0Z",
      "ref": "v23.0.0"
    },
    "24.0.0": {
      "bytes": 22194,
      "hash": "sha256-vyu81sBQ1r29j7qEcGFWwttT2Nn3rU6XVcOVNjQ59ZU=",
      "publishedTime": "2017-05-08T11:55:29.0Z",
      "ref": "v24.0.0"
    },
    "25.0.0": {
      "bytes": 22488,
      "hash": "sha256-zEyA5eTHU7pOIsqkv3A8Ei1zwBIVr9sibYJiM6hDa3M=",
      "publishedTime": "2017-05-25T18:50:31.0Z",
      "ref": "v25.0.0"
    },
    "25.0.1": {
      "bytes": 22498,
      "hash": "sha256-G3l/VRE8Cdgsmb5WGmUnBNV1VotdOcOELa9b6V70S2w=",
      "publishedTime": "2017-05-25T22:41:10.0Z",
      "ref": "v25.0.1"
    },
    "26.0.0": {
      "bytes": 23606,
      "hash": "sha256-x3DKIVaxIEjTbb84wApjV6OuFDGO0MBiNcxL3e4vHJA=",
      "publishedTime": "2017-06-06T14:25:25.0Z",
      "ref": "v26.0.0"
    },
    "27.0.0": {
      "bytes": 24186,
      "hash": "sha256-Z153rSu/BlYS3E4FoABmFaq40tbwYUaLRUvmhMpV+iM=",
      "publishedTime": "2017-06-07T01:51:20.0Z",
      "ref": "v27.0.0"
    },
    "28.0.0": {
      "bytes": 24315,
      "hash": "sha256-YvjuPGUjeHGyB77FZu1U3nTQqQf6QlFE3EHu3amsvKI=",
      "publishedTime": "2017-06-07T10:56:54.0Z",
      "ref": "v28.0.0"
    },
    "29.0.0": {
      "bytes": 25463,
      "hash": "sha256-S8eFpeLtNoeg21c+uvCN+ju4eW932vBX8hRWVkVj97U=",
      "publishedTime": "2017-06-08T22:06:41.0Z",
      "ref": "v29.0.0"
    },
    "30.0.0": {
      "bytes": 25625,
      "hash": "sha256-Ulvm/3Q3BJYAS5ojc/sIwWw73lJtInjabYmXkekmHjE=",
      "publishedTime": "2017-06-27T15:09:56.0Z",
      "ref": "v30.0.0"
    },
    "31.0.0": {
      "bytes": 25646,
      "hash": "sha256-tqX/4VCNvkYq8QZYVnarhr7a8Zd19SLRwZNvmtYk3Sk=",
      "publishedTime": "2017-06-30T12:07:15.0Z",
      "ref": "v31.0.0"
    },
    "31.1.0": {
      "bytes": 25850,
      "hash": "sha256-3N8DPE1X7ut5iyttfFpXCk6q05VcR1hf79g6m3oWDjM=",
      "publishedTime": "2017-07-21T13:48:50.0Z",
      "ref": "v31.1.0"
    },
    "32.0.0": {
      "bytes": 25871,
      "hash": "sha256-5TuRW/JCzCWXsTiyfuyq2HQ0pOJ3Na/bqF91TdDfJug=",
      "publishedTime": "2017-07-21T13:58:42.0Z",
      "ref": "v32.0.0"
    },
    "33.0.0": {
      "bytes": 26426,
      "hash": "sha256-02rlPzNQ4ifCWz2EZepk1+2yo+WEpoEmV9nTyrE6KMk=",
      "publishedTime": "2017-07-28T12:58:03.0Z",
      "ref": "v33.0.0"
    },
    "34.0.0": {
      "bytes": 26642,
      "hash": "sha256-a0ydUlKwGOhxZVhS2nykjunnpU+CBJl53zPe84365w4=",
      "publishedTime": "2017-07-31T10:24:15.0Z",
      "ref": "v34.0.0"
    },
    "35.0.0": {
      "bytes": 26967,
      "hash": "sha256-iNeBxISaDo1DSWL9iu3FTx5Rq/Q7YEeXK8TpUxFt0+o=",
      "publishedTime": "2017-08-04T14:39:48.0Z",
      "ref": "v35.0.0"
    },
    "35.0.1": {
      "bytes": 26975,
      "hash": "sha256-wwRU9q3mL2n4wuBFLYDZVA0CKcdbsDYrFln0YmrvHjs=",
      "publishedTime": "2017-08-10T15:26:39.0Z",
      "ref": "v35.0.1"
    },
    "36.0.0": {
      "bytes": 26969,
      "hash": "sha256-6EACD/8sQjTeuiqbZXD0U55t3C8s8jHCVA/Xjvxgmdg=",
      "publishedTime": "2017-09-08T18:00:33.0Z",
      "ref": "v36.0.0"
    },
    "37.0.0": {
      "bytes": 27164,
      "hash": "sha256-TSZ4YIHweb+mRny8dGySBcqrr89n5OzYrH1F45kNenw=",
      "publishedTime": "2017-09-09T16:31:57.0Z",
      "ref": "v37.0.0"
    },
    "38.0.0": {
      "bytes": 27844,
      "hash": "sha256-WcMxb8aDlXK+182LLhzxycFgm0sfnB93WwCtF/I1RvQ=",
      "publishedTime": "2017-09-28T13:41:11.0Z",
      "ref": "v38.0.0"
    },
    "38.0.1": {
      "bytes": 27853,
      "hash": "sha256-67WmhiQbbWqwll6iDde34BXZmJ3aBq1/SxtvO2FI0wg=",
      "publishedTime": "2017-10-02T11:51:44.0Z",
      "ref": "v38.0.1"
    },
    "38.0.2": {
      "bytes": 27889,
      "hash": "sha256-VAHkTkEPXOpfe/vw5uCm38ZyplJ7+xgs7M11j0SI18k=",
      "publishedTime": "2017-10-02T16:06:18.0Z",
      "ref": "v38.0.2"
    },
    "38.0.3": {
      "bytes": 27913,
      "hash": "sha256-lwmMSdNPkLT+EFhclwOHuGA0fzCspOtD0YxpiMydD94=",
      "publishedTime": "2017-10-03T14:49:16.0Z",
      "ref": "v38.0.3"
    },
    "38.0.4": {
      "bytes": 27891,
      "hash": "sha256-LYYRIb6egODbU2BkljnPbVqyjZDlOc1IaxcUo35stp4=",
      "publishedTime": "2017-10-03T15:22:35.0Z",
      "ref": "v38.0.4"
    },
    "38.0.5": {
      "bytes": 27992,
      "hash": "sha256-CN8mBLf2geSQs1/JS9pR2OLuPrgvmmW3HhrQTJViSlo=",
      "publishedTime": "2017-10-05T14:00:01.0Z",
      "ref": "v38.0.5"
    },
    "38.0.6": {
      "bytes": 28026,
      "hash": "sha256-iIotHlwFL89PJwIdRnojAPTKcKcMpQcX6R96GmqqHTk=",
      "publishedTime": "2017-10-13T12:09:51.0Z",
      "ref": "v38.0.6"
    },
    "38.1.0": {
      "bytes": 28031,
      "hash": "sha256-j/rQusmhjhZLP18/p8s4Tt1ohHTpDBF1gs24vToUT6A=",
      "publishedTime": "2017-10-17T13:49:43.0Z",
      "ref": "v38.1.0"
    },
    "38.2.0": {
      "bytes": 28378,
      "hash": "sha256-xeEJD/mXtJTT4v5wIu4kB1RzrlLzenRq2bSEusdWin4=",
      "publishedTime": "2017-10-19T11:03:49.0Z",
      "ref": "v38.2.0"
    },
    "39.0.0": {
      "bytes": 28630,
      "hash": "sha256-ZmkugbLJ8bd2mnZuz8isRb4f9jMIPbWL6j8GrTLGfPA=",
      "publishedTime": "2017-10-29T20:04:00.0Z",
      "ref": "v39.0.0"
    },
    "40.0.0": {
      "bytes": 30511,
      "hash": "sha256-o0TOh9vrPsO8fH5HsGbrgs6z/St/M/A4uiX8mu3gqOo=",
      "publishedTime": "2017-11-08T16:46:46.0Z",
      "ref": "v40.0.0"
    },
    "40.1.0": {
      "bytes": 30686,
      "hash": "sha256-5R7HhLzBrvcF5CNJBcwp+OQ9nZBKUpyMjids5cD4NY8=",
      "publishedTime": "2017-11-17T15:42:30.0Z",
      "ref": "v40.1.0"
    },
    "40.1.1": {
      "bytes": 30695,
      "hash": "sha256-wnXPmgUjmx9WjK+cq7d+fBM9L2gFUENDmRdikBQMT9w=",
      "publishedTime": "2017-12-19T15:14:43.0Z",
      "ref": "v40.1.1"
    },
    "40.1.2": {
      "bytes": 30710,
      "hash": "sha256-1kFNsrFyffoTNNd33jRDOzEWTAdZfsOHts47ZoHn9AM=",
      "publishedTime": "2017-12-19T15:30:20.0Z",
      "ref": "v40.1.2"
    },
    "41.0.0": {
      "bytes": 30585,
      "hash": "sha256-wK1rfVrkeyTPlMUm/8G+bVGuFxH1g4ongjQgVSUmJGY=",
      "publishedTime": "2017-12-22T14:25:17.0Z",
      "ref": "v41.0.0"
    },
    "41.0.1": {
      "bytes": 30597,
      "hash": "sha256-pAkDykaD5qoHBjUiHkw4bS4Ma5X0I5WW1FxoaavSazs=",
      "publishedTime": "2018-01-12T14:27:40.0Z",
      "ref": "v41.0.1"
    },
    "42.0.0": {
      "bytes": 30515,
      "hash": "sha256-yqZaB9ySFzYQzO8+G3Olk+sg/BTZI/Ca+gpXqgKgGZw=",
      "publishedTime": "2018-01-15T10:45:33.0Z",
      "ref": "v42.0.0"
    },
    "42.0.1": {
      "bytes": 30524,
      "hash": "sha256-+V+UWwdGdbftPQk2/btOx9exBkiq/27k0oB+27ofREI=",
      "publishedTime": "2018-01-17T15:04:43.0Z",
      "ref": "v42.0.1"
    },
    "43.0.0": {
      "bytes": 30541,
      "hash": "sha256-HzcBpB6mp4v7N2+MQ9dIz8Oq4Ue36+ujkMMM1WP7/rc=",
      "publishedTime": "2018-01-24T12:49:31.0Z",
      "ref": "v43.0.0"
    },
    "43.1.0": {
      "bytes": 30583,
      "hash": "sha256-jbV9UL2RwINxdDSFVrQV5xv141nYzXA+VhzimwOtuEU=",
      "publishedTime": "2018-02-27T10:14:04.0Z",
      "ref": "v43.1.0"
    },
    "43.1.1": {
      "bytes": 31009,
      "hash": "sha256-FDZtxUzFzrrrg14RsSoFmTPNnNPsdOyjNW6Uqt4eEKY=",
      "publishedTime": "2018-02-28T09:46:48.0Z",
      "ref": "v43.1.1"
    },
    "44.0.0": {
      "bytes": 31083,
      "hash": "sha256-+5SBccIJrbya1KNpedxlx+U9nbP8iDRhr/MCQw3W/qM=",
      "publishedTime": "2018-03-16T12:17:19.0Z",
      "ref": "v44.0.0"
    },
    "45.0.0": {
      "bytes": 33456,
      "hash": "sha256-GRX3AQ8JC7dCDwrDsIwpzC0W48L7SdOO4XjdAsdhLFs=",
      "publishedTime": "2018-03-20T22:12:10.0Z",
      "ref": "v45.0.0"
    }
  },
  "unpublished": {}
}
