{
  "location": {
    "githubOwner": "the-dr-lazy",
    "githubRepo": "purescript-quickcheck-state-machine"
  },
  "published": {
    "0.0.2": {
      "bytes": 3223,
      "hash": "sha256-j59ho7tZmdqv7Kvc4Gzr75EHYiT0mZjuGwBkH77Z2/U=",
      "publishedTime": "2020-06-17T18:43:35.0Z",
      "ref": "v0.0.2"
    },
    "0.0.3": {
      "bytes": 5492,
      "hash": "sha256-ST3FwqS2prF9igx8miMByIpZDOzZ9qlHOuzeSC95wJ8=",
      "publishedTime": "2020-06-17T19:47:38.0Z",
      "ref": "v0.0.3"
    },
    "0.0.4": {
      "bytes": 5491,
      "hash": "sha256-gPcdS++7X7KINbprqI/OqU4XFRj472hlCevEqmdevDY=",
      "publishedTime": "2020-06-21T13:48:31.0Z",
      "ref": "v0.0.4"
    },
    "0.0.5": {
      "bytes": 5874,
      "hash": "sha256-RP6OWKtG0hJ46CY26q0iLt7+F2W3684/AT5PL284Wro=",
      "publishedTime": "2020-06-25T05:46:37.0Z",
      "ref": "v0.0.5"
    },
    "0.0.6": {
      "bytes": 5640,
      "hash": "sha256-08RHlFLVCQcxImwqlhyqoKKulSvTHrJcb48WFHSCysc=",
      "publishedTime": "2020-06-25T07:33:03.0Z",
      "ref": "v0.0.6"
    },
    "0.0.7": {
      "bytes": 5603,
      "hash": "sha256-hfB96SsSW/TJVov+G9EYlZlpQAJBnIt73TWyoIJYQ7A=",
      "publishedTime": "2020-06-25T07:33:58.0Z",
      "ref": "v0.0.7"
    },
    "0.0.8": {
      "bytes": 5634,
      "hash": "sha256-sTObfVspEjV/sN2sMV3O7vXcy/+NUQf64TM9WPqWDrE=",
      "publishedTime": "2020-06-26T09:21:42.0Z",
      "ref": "v0.0.8"
    },
    "0.0.9": {
      "bytes": 5559,
      "hash": "sha256-3h2h7alGVlIhQ77Hxh1hEtJawDvOH+wG0CLAebpVwwA=",
      "publishedTime": "2020-07-13T05:26:57.0Z",
      "ref": "v0.0.9"
    }
  },
  "unpublished": {}
}
