{
  "location": {
    "githubOwner": "coot",
    "githubRepo": "purescript-react-ix"
  },
  "published": {
    "0.1.1": {
      "bytes": 9432,
      "hash": "sha256-14TV+dhlpWRojh/NX1bTq75Gx9AxnWBYyV3ielrJRSc=",
      "publishedTime": "2017-07-22T12:04:47.0Z",
      "ref": "v0.1.1"
    },
    "0.1.2": {
      "bytes": 9417,
      "hash": "sha256-JXgpBu81o2Otej9UZEYxd0PhmB5XsVjqtZf4ejyvxKc=",
      "publishedTime": "2017-07-22T12:06:47.0Z",
      "ref": "v0.1.2"
    },
    "0.2.0": {
      "bytes": 9387,
      "hash": "sha256-RAgDaJ9LVuARco34NqgXRJ6i5hklRdXE/U4E8iD9mQc=",
      "publishedTime": "2017-07-22T17:47:57.0Z",
      "ref": "v0.2.0"
    },
    "0.3.0": {
      "bytes": 9518,
      "hash": "sha256-6O+2cSRtMXR5k1XbH3eyKozX+ZtaL3IyAapSqwhgMek=",
      "publishedTime": "2017-07-22T18:46:04.0Z",
      "ref": "v0.3.0"
    },
    "0.3.1": {
      "bytes": 9647,
      "hash": "sha256-uk4P1tk/iSTgBHcVRw9LTkcVYF9uR2Mv/yjkkwDxZlc=",
      "publishedTime": "2017-07-22T19:02:07.0Z",
      "ref": "v0.3.1"
    },
    "0.4.0": {
      "bytes": 9841,
      "hash": "sha256-w/TStPj0kvvtTaVXUo3rptB45oMp8aL8YP2XPUcWjJE=",
      "publishedTime": "2017-07-22T20:19:50.0Z",
      "ref": "v0.4.0"
    },
    "0.5.0": {
      "bytes": 9858,
      "hash": "sha256-MqvkpqHdbuyPVb5t1L7SODvsOTjCao9P3SnMapmcoVc=",
      "publishedTime": "2017-07-23T12:18:12.0Z",
      "ref": "v0.5.0"
    },
    "0.5.1": {
      "bytes": 9843,
      "hash": "sha256-wS0hfBN52yCpjdxVKaoo4xCPWnKePNq2y2YytO9h0Oc=",
      "publishedTime": "2017-09-05T20:31:37.0Z",
      "ref": "v0.5.1"
    },
    "0.5.2": {
      "bytes": 9865,
      "hash": "sha256-6eN9fBZAAqPvCdQKxZCgC4p2R9VUu9IESJ3KkULV8mM=",
      "publishedTime": "2017-09-27T15:35:52.0Z",
      "ref": "v0.5.2"
    },
    "0.5.3": {
      "bytes": 9889,
      "hash": "sha256-vuh88hMRGjv6T7WSu6pmXnOn2pnCnMEERl/RhqAdWU8=",
      "publishedTime": "2017-10-07T18:52:21.0Z",
      "ref": "v0.5.3"
    }
  },
  "unpublished": {}
}
