{
  "location": {
    "githubOwner": "pkamenarsky",
    "githubRepo": "purescript-refract"
  },
  "published": {
    "0.0.2": {
      "bytes": 15302,
      "hash": "sha256-If/d7k5XeX3+Q4KYb9IxffH2oS2idVPRaQytr6/dN6s=",
      "publishedTime": "2018-02-02T13:48:39.0Z",
      "ref": "v0.0.2"
    },
    "0.0.3": {
      "bytes": 15299,
      "hash": "sha256-vGQDUOFWWzPbUUf9KR4Tf8dinMma91eqvSW9i5Lr744=",
      "publishedTime": "2018-02-02T13:53:50.0Z",
      "ref": "v0.0.3"
    }
  },
  "unpublished": {}
}
