{
  "location": {
    "githubOwner": "reactormonk",
    "githubRepo": "purescript-simple-timestamp"
  },
  "published": {
    "1.0.0": {
      "bytes": 3296,
      "hash": "sha256-vjTn/Adm3YM1/GMZQ3QSziCPLHPfqvsoX8zLUuuhVzU=",
      "publishedTime": "2019-07-04T07:55:16.0Z",
      "ref": "v1.0.0"
    },
    "1.1.0": {
      "bytes": 3315,
      "hash": "sha256-lBEte6FhDFM00TQjKa5ZAEQ89vCWRxFPegq1QVp0cS0=",
      "publishedTime": "2019-07-04T11:31:44.0Z",
      "ref": "v1.1.0"
    },
    "1.2.0": {
      "bytes": 3386,
      "hash": "sha256-aGnVrXXiHft8pk7SkC3swWGqOdUtg8YIVdFWyMLD2hE=",
      "publishedTime": "2019-07-05T07:33:06.0Z",
      "ref": "v1.2.0"
    },
    "1.3.0": {
      "bytes": 3408,
      "hash": "sha256-5h2sGoY0uELP4/pCAbKl+FXWrUTrljaHhUXrJrL6cTA=",
      "publishedTime": "2019-07-05T12:56:01.0Z",
      "ref": "v1.3.0"
    },
    "2.0.0": {
      "bytes": 3409,
      "hash": "sha256-ZOOxub/zSDeg/vC2j0dfV2JLy73ebIokZzLtK7KfAwM=",
      "publishedTime": "2019-10-08T14:29:58.0Z",
      "ref": "v2.0.0"
    },
    "3.0.0": {
      "bytes": 3788,
      "hash": "sha256-fzhnW6UrFF8NIEz1OgmkNBKCrPQCkEsp3pHxTvDPNiA=",
      "publishedTime": "2019-10-11T18:23:18.0Z",
      "ref": "v3.0.0"
    }
  },
  "unpublished": {}
}
