{
  "location": {
    "githubOwner": "purescript-web",
    "githubRepo": "purescript-web-dom-xpath"
  },
  "published": {
    "1.0.0": {
      "bytes": 3763,
      "hash": "sha256-RAsNi5SltAVMl9NyD0C5le+JnwL+xhGw41Hkq2zeCYI=",
      "publishedTime": "2019-04-19T19:30:11.000Z",
      "ref": "v1.0.0"
    },
    "1.0.1": {
      "bytes": 3760,
      "hash": "sha256-GP3WvL8bu4bVfiR+xyr3474/1gEYBgLvnGOTQRydilI=",
      "publishedTime": "2019-04-19T20:01:23.000Z",
      "ref": "v1.0.1"
    },
    "1.0.2": {
      "bytes": 3755,
      "hash": "sha256-pxwD9RDuPSOPmHAd4qGHvRxuJvC82cOHKaiF0URniOY=",
      "publishedTime": "2019-04-19T20:23:57.000Z",
      "ref": "v1.0.2"
    },
    "1.1.0": {
      "bytes": 4504,
      "hash": "sha256-SZuAZzPSLUO4NaqriDYcKS2oO6y1Ly8KtGOB4kjgiFE=",
      "publishedTime": "2019-04-23T19:53:49.000Z",
      "ref": "v1.1.0"
    },
    "1.2.0": {
      "bytes": 4646,
      "hash": "sha256-Ke7Di1YCf/HcFGK9tArTpdhKR6L1KtoIjNJ2pH5lDU8=",
      "publishedTime": "2019-04-23T21:34:48.000Z",
      "ref": "v1.2.0"
    },
    "1.2.1": {
      "bytes": 4646,
      "hash": "sha256-c39WPVtYkdpORZC184N6g1KUvlJweS6B7jr9djrX1p0=",
      "publishedTime": "2019-06-26T19:50:53.000Z",
      "ref": "v1.2.1"
    },
    "1.2.2": {
      "bytes": 4646,
      "hash": "sha256-0dmpnxKEiJvu/Vy2odQTSdhJ3wySIQQpyPEdvfe0V44=",
      "publishedTime": "2019-08-18T14:06:27.000Z",
      "ref": "v1.2.2"
    },
    "2.0.0": {
      "bytes": 4620,
      "hash": "sha256-eX+MHKI+VtS0Q111P0qeiUUCxyWRFaerH9MhJk8Y/GQ=",
      "publishedTime": "2021-02-26T21:26:53.000Z",
      "ref": "v2.0.0"
    },
    "2.0.1": {
      "bytes": 4621,
      "hash": "sha256-OhcvHgAagp3ETkOFfyvObzTPoht/8DKm+kOdtzG7/+k=",
      "publishedTime": "2021-05-06T16:46:02.000Z",
      "ref": "v2.0.1"
    },
    "3.0.0": {
      "bytes": 4624,
      "hash": "sha256-pALaKPFhcs3m5LfAlLSN5MfulYRaDYt3MRSs8706HGg=",
      "publishedTime": "2022-04-27T23:25:50.000Z",
      "ref": "v3.0.0"
    }
  },
  "unpublished": {}
}
