{
  "location": {
    "githubOwner": "mjepronk",
    "githubRepo": "purescript-web-url"
  },
  "published": {
    "1.0.1": {
      "bytes": 4559,
      "hash": "sha256-Bu0tH6gThvGXg+uhn+LoZSVqfDgSYgFIs+5wHP0PPj0=",
      "publishedTime": "2020-06-08T20:19:56.0Z",
      "ref": "v1.0.1"
    },
    "1.0.2": {
      "bytes": 4559,
      "hash": "sha256-S+GLfexl0H4teBGcZtOrWGU7g4JtFSNQeZLZLCv36Ds=",
      "publishedTime": "2020-06-14T16:09:12.0Z",
      "ref": "v1.0.2"
    },
    "2.0.0": {
      "bytes": 4571,
      "hash": "sha256-WQmAnKF1YloAJRh68IMRjLNaqf1Tnm/MdDH2B6+1r9w=",
      "publishedTime": "2022-07-07T15:52:40.0Z",
      "ref": "v2.0.0"
    }
  },
  "unpublished": {}
}
