{
  "location": {
    "githubOwner": "mitchellandwebb",
    "githubRepo": "webb-commandline"
  },
  "published": {
    "0.0.1": {
      "bytes": 1198,
      "compilers": [
        "0.15.0",
        "0.15.2",
        "0.15.3",
        "0.15.4",
        "0.15.5",
        "0.15.6",
        "0.15.7",
        "0.15.8",
        "0.15.9",
        "0.15.10",
        "0.15.11",
        "0.15.12",
        "0.15.13",
        "0.15.14",
        "0.15.15"
      ],
      "hash": "sha256-OpnYjpCS6EH223MbZp55BeztgO8r9MXSKtdueWWv440=",
      "publishedTime": "2025-12-27T02:39:01.000Z"
    },
    "0.0.2": {
      "bytes": 1355,
      "compilers": [
        "0.15.0",
        "0.15.2",
        "0.15.3",
        "0.15.4",
        "0.15.5",
        "0.15.6",
        "0.15.7",
        "0.15.8",
        "0.15.9",
        "0.15.10",
        "0.15.11",
        "0.15.12",
        "0.15.13",
        "0.15.14",
        "0.15.15"
      ],
      "hash": "sha256-vg7nzaGHOQ/4zGO7gSuD36cml9RlEI6h7pC9AePTe1M=",
      "publishedTime": "2025-12-27T03:49:14.000Z"
    },
    "0.0.3": {
      "bytes": 1402,
      "compilers": [
        "0.15.0",
        "0.15.2",
        "0.15.3",
        "0.15.4",
        "0.15.5",
        "0.15.6",
        "0.15.7",
        "0.15.8",
        "0.15.9",
        "0.15.10",
        "0.15.11",
        "0.15.12",
        "0.15.13",
        "0.15.14",
        "0.15.15"
      ],
      "hash": "sha256-XYMg2s/Ud6y9xdPYn3LSuPwkYElmciEJI6rKiesQL4I=",
      "publishedTime": "2025-12-27T18:20:42.000Z"
    }
  },
  "unpublished": {}
}
