{
  "location": {
    "githubOwner": "cdepillabout",
    "githubRepo": "purescript-words-lines"
  },
  "published": {
    "0.0.1": {
      "bytes": 2358,
      "hash": "sha256-ZzA6qmDN11a049yvTfLIhHyPSW/AezGWKgkUSSU30Jc=",
      "publishedTime": "2016-02-01T16:37:49.0Z",
      "ref": "v0.0.1"
    },
    "0.0.2": {
      "bytes": 2365,
      "hash": "sha256-9eOrsRyO2yitF3cCkiIIolPuotmAhqYGP11WAv2VnAg=",
      "publishedTime": "2016-02-02T13:46:27.0Z",
      "ref": "v0.0.2"
    },
    "0.0.3": {
      "bytes": 2366,
      "hash": "sha256-+pe4jhkCHOftMBnWbOovYACdm9Lnkfe/of4rh+huB2A=",
      "publishedTime": "2016-04-29T15:05:06.0Z",
      "ref": "v0.0.3"
    },
    "0.0.4": {
      "bytes": 2365,
      "hash": "sha256-toKCgPCdwIAONxmYJvOFvJ4inAk3cAskLD+uwY7iuWM=",
      "publishedTime": "2016-04-29T15:10:54.0Z",
      "ref": "v0.0.4"
    },
    "0.0.5": {
      "bytes": 3201,
      "hash": "sha256-LkeRavvyG7fcduma+OBhFmRLCyU0LyaR/CkLAdP+eWU=",
      "publishedTime": "2016-04-29T15:17:02.0Z",
      "ref": "v0.0.5"
    }
  },
  "unpublished": {}
}
